snowkill/__init__.py
snowkill/engine.py
snowkill/error.py
snowkill/struct.py
snowkill/version.py
snowkill/condition/__init__.py
snowkill/condition/abc_condition.py
snowkill/condition/blocked_duration.py
snowkill/condition/cartesian_join_explosion.py
snowkill/condition/estimated_scan_duration.py
snowkill/condition/execute_duration.py
snowkill/condition/join_explosion.py
snowkill/condition/queued_duration.py
snowkill/condition/storage_spilling.py
snowkill/condition/union_without_all.py
snowkill/formatter/__init__.py
snowkill/formatter/abc_formatter.py
snowkill/formatter/markdown.py
snowkill/formatter/slack.py
snowkill/storage/__init__.py
snowkill/storage/abc_storage.py
snowkill/storage/postgres_table.py
snowkill/storage/snowflake_hybrid_table.py
snowkill/storage/snowflake_table.py
snowkill-0.5.0.dist-info/LICENSE.txt
snowkill-0.5.0.dist-info/METADATA
snowkill-0.5.0.dist-info/WHEEL
snowkill-0.5.0.dist-info/top_level.txt
snowkill-0.5.0.dist-info/RECORD
