Metadata-Version: 2.1
Name: snowkill
Version: 0.5.0
Summary: A tool for realtime monitoring of running, queued and blocked queries in Snowflake
Home-page: https://github.com/littleK0i/snowkill
Author: Vitaly Markov
Author-email: wild.desu@gmail.com
Keywords: snowflake,sql,query,monitor,monitoring,running,kill,terminate,database
Classifier: Development Status :: 4 - Beta
Classifier: License :: OSI Approved :: Apache Software License
Classifier: Operating System :: OS Independent
Classifier: Intended Audience :: Developers
Classifier: Topic :: Database
Classifier: Programming Language :: Python :: 3.8
Classifier: Programming Language :: Python :: 3.9
Classifier: Programming Language :: Python :: 3.10
Classifier: Programming Language :: Python :: 3.11
Requires-Python: >=3.8
License-File: LICENSE.txt
Requires-Dist: snowflake-connector-python
Provides-Extra: examples
Requires-Dist: markdown; extra == "examples"
Requires-Dist: psycopg[binary]; extra == "examples"
Requires-Dist: requests; extra == "examples"
Provides-Extra: postgres
Requires-Dist: psycopg[binary]; extra == "postgres"
Provides-Extra: dev
Requires-Dist: black; extra == "dev"
Requires-Dist: pytest; extra == "dev"
Requires-Dist: ruff; extra == "dev"
